{"errors":[],"warnings":[],"namedChunkGroups":{"polyfill":{"chunks":[2,0,7],"assets":["webpack-runtime-ff452b069b810b6e5b43.js","webpack-runtime-ff452b069b810b6e5b43.js.map","commons-c4bb1ab5b85cdfa684d7.js","commons-c4bb1ab5b85cdfa684d7.js.map","polyfill-5acc46d2c6294ee52fa0.js","polyfill-5acc46d2c6294ee52fa0.js.map"],"children":{},"childAssets":{}},"app":{"chunks":[2,6,0,3],"assets":["webpack-runtime-ff452b069b810b6e5b43.js","webpack-runtime-ff452b069b810b6e5b43.js.map","framework-d066f55745d479a55fde.js","framework-d066f55745d479a55fde.js.map","commons-c4bb1ab5b85cdfa684d7.js","commons-c4bb1ab5b85cdfa684d7.js.map","app-9f0e29af14fd8d5cd5ed.js","app-9f0e29af14fd8d5cd5ed.js.map"],"children":{},"childAssets":{}},"component---src-pages-404-js":{"chunks":[1,0,4],"assets":["styles.e6b8ff5a609ff03a2a5f.css","styles-e9d24b1846c7d6eb9685.js","styles-e9d24b1846c7d6eb9685.js.map","commons-c4bb1ab5b85cdfa684d7.js","commons-c4bb1ab5b85cdfa684d7.js.map","component---src-pages-404-js-0db82d6eeee6490b835e.js","component---src-pages-404-js-0db82d6eeee6490b835e.js.map"],"children":{},"childAssets":{}},"component---src-pages-index-js":{"chunks":[1,0,5],"assets":["styles.e6b8ff5a609ff03a2a5f.css","styles-e9d24b1846c7d6eb9685.js","styles-e9d24b1846c7d6eb9685.js.map","commons-c4bb1ab5b85cdfa684d7.js","commons-c4bb1ab5b85cdfa684d7.js.map","component---src-pages-index-js-435d368865359c6f7729.js","component---src-pages-index-js-435d368865359c6f7729.js.map"],"children":{},"childAssets":{}}},"assetsByChunkName":{"polyfill":["webpack-runtime-ff452b069b810b6e5b43.js","commons-c4bb1ab5b85cdfa684d7.js","polyfill-5acc46d2c6294ee52fa0.js"],"app":["webpack-runtime-ff452b069b810b6e5b43.js","framework-d066f55745d479a55fde.js","commons-c4bb1ab5b85cdfa684d7.js","app-9f0e29af14fd8d5cd5ed.js"],"component---src-pages-404-js":["styles.e6b8ff5a609ff03a2a5f.css","styles-e9d24b1846c7d6eb9685.js","commons-c4bb1ab5b85cdfa684d7.js","component---src-pages-404-js-0db82d6eeee6490b835e.js"],"component---src-pages-index-js":["styles.e6b8ff5a609ff03a2a5f.css","styles-e9d24b1846c7d6eb9685.js","commons-c4bb1ab5b85cdfa684d7.js","component---src-pages-index-js-435d368865359c6f7729.js"]}}